LICENSE.txt
MANIFEST.in
README.rst
setup.py
plonetheme/__init__.py
plonetheme/__init__.pyc
plonetheme.html5_hotpink.egg-info/PKG-INFO
plonetheme.html5_hotpink.egg-info/SOURCES.txt
plonetheme.html5_hotpink.egg-info/dependency_links.txt
plonetheme.html5_hotpink.egg-info/entry_points.txt
plonetheme.html5_hotpink.egg-info/namespace_packages.txt
plonetheme.html5_hotpink.egg-info/not-zip-safe
plonetheme.html5_hotpink.egg-info/requires.txt
plonetheme.html5_hotpink.egg-info/top_level.txt
plonetheme/html5_hotpink/.DS_Store
plonetheme/html5_hotpink/__init__.py
plonetheme/html5_hotpink/__init__.pyc
plonetheme/html5_hotpink/configure.zcml
plonetheme/html5_hotpink/static/about.html
plonetheme/html5_hotpink/static/contact.html
plonetheme/html5_hotpink/static/index.html
plonetheme/html5_hotpink/static/license.txt
plonetheme/html5_hotpink/static/manifest.cfg
plonetheme/html5_hotpink/static/rules.xml
plonetheme/html5_hotpink/static/css/custom.css
plonetheme/html5_hotpink/static/css/fonts.css
plonetheme/html5_hotpink/static/css/plone.css
plonetheme/html5_hotpink/static/css/style.css
plonetheme/html5_hotpink/static/fonts/DroidSerif-Bold.woff
plonetheme/html5_hotpink/static/fonts/DroidSerif.woff
plonetheme/html5_hotpink/static/images/accepted.png
plonetheme/html5_hotpink/static/images/bg.png
plonetheme/html5_hotpink/static/images/cancel.png
plonetheme/html5_hotpink/static/images/pb_close.png
plonetheme/html5_hotpink/static/images/quote.png
plonetheme/html5_hotpink/static/images/search.png
plonetheme/html5_hotpink/static/images/thumbnail.jpg
plonetheme/html5_hotpink/static/js/ie.html
plonetheme/html5_hotpink/static/js/modernizr-1.7.min.js
plonetheme/html5_hotpink/static/js/respond.min.js
plonetheme/html5_hotpink/static/js/script.js