Metadata-Version: 1.0
Name: plonetheme.html5-hotpink
Version: 0.1
Summary: Diazo theme for Plone
Home-page: https://github.com/garbas/plonetheme.html5_hotpink
Author: Rok Garbas
Author-email: rok@garbas.si
License: BSD
Keywords: plone diazo theme
Platform: UNKNOWN
Classifier: Framework :: Plone
Classifier: Programming Language :: Python
Classifier: License :: OSI Approved :: BSD License
